Workbook

Sheet Rides
A1: Ride_ID | B1: Platform | C1: Category | D1: Date | E1: Start_Time | F1: End_Time | G1: Duration_Min | H1: Origin_PostCode | I1: Dest_PostCode | J1: Distance_Km | K1: Client_Fare_EUR | L1: Driver_Earnings_EUR | M1: Platform_Fee_EUR | N1: Fee_Pct | O1: EUR_per_Km | P1: EUR_per_Min | Q1: Portagem | R1: Dinamica | S1: Tip
A2: R013 | B2: Uber | C2: Uber X | D2: 46085 | E2: 0.81180556 | F2: 0.82916667 | G2: =(F2-E2)*1440 -> 25 | H2: 2785-115 | I2: 2675-663 | J2: 24.44 | K2: 14.69 | L2: 9.66 | M2: =K2-L2 -> 5.03 | N2: =IFERROR(M2/K2,0) -> 0.3424098 | O2: =IFERROR(L2/J2,0) -> 0.39525368 | P2: =IFERROR(L2/G2,0) -> 0.3864 | Q2: 0.7
A3: R003 | B3: Bolt | C3: Economy | D3: 46085 | E3: 0.83888889 | F3: 0.84930556 | G3: =(F3-E3)*1440 -> 15 | H3: 2675-472 | I3: 1600-196 | J3: 10.2 | K3: 5.9 | L3: 4.42 | M3: =K3-L3 -> 1.48 | N3: =IFERROR(M3/K3,0) -> 0.25084746 | O3: =IFERROR(L3/J3,0) -> 0.43333333 | P3: =IFERROR(L3/G3,0) -> 0.29466667
A4: R009 | B4: Uber | C4: Uber X | D4: 46085 | E4: 0.70069444 | F4: 0.71666667 | G4: =(F4-E4)*1440 -> 23 | H4: 2635-304 | I4: 2610-244 | J4: 14.49 | K4: 9.93 | L4: 6.87 | M4: =K4-L4 -> 3.06 | N4: =IFERROR(M4/K4,0) -> 0.3081571 | O4: =IFERROR(L4/J4,0) -> 0.47412008 | P4: =IFERROR(L4/G4,0) -> 0.29869565
A5: R005 | B5: Uber | C5: Uber X | D5: 46085 | E5: 0.5875 | F5: 0.60416667 | G5: =(F5-E5)*1440 -> 24 | H5: 2690-182 | I5: 1250-096 | J5: 16.6 | K5: 10.96 | L5: 7.99 | M5: =K5-L5 -> 2.97 | N5: =IFERROR(M5/K5,0) -> 0.2709854 | O5: =IFERROR(L5/J5,0) -> 0.4813253 | P5: =IFERROR(L5/G5,0) -> 0.33291667
A6: R002 | B6: Bolt | C6: Economy | D6: 46085 | E6: 0.79930556 | F6: 0.81666667 | G6: =(F6-E6)*1440 -> 25 | H6: 1500-663 | I6: 2785-816 | J6: 17.2 | K6: 11.66 | L6: 8.92 | M6: =K6-L6 -> 2.74 | N6: =IFERROR(M6/K6,0) -> 0.23499142 | O6: =IFERROR(L6/J6,0) -> 0.51860465 | P6: =IFERROR(L6/G6,0) -> 0.3568
A7: R010 | B7: Uber | C7: Uber X Priority | D7: 46085 | E7: 0.72638889 | F7: 0.73541667 | G7: =(F7-E7)*1440 -> 13 | H7: 2720-145 | I7: 2790-226 | J7: 8.07 | K7: 5.97 | L7: 4.21 | M7: =K7-L7 -> 1.76 | N7: =IFERROR(M7/K7,0) -> 0.29480737 | O7: =IFERROR(L7/J7,0) -> 0.52168525 | P7: =IFERROR(L7/G7,0) -> 0.32384615
A8: R006 | B8: Uber | C8: Uber X | D8: 46085 | E8: 0.60833333 | F8: 0.61805556 | G8: =(F8-E8)*1440 -> 14 | H8: 1070-100 | I8: 1300-294 | J8: 7.16 | K8: 5.94 | L8: 3.86 | M8: =K8-L8 -> 2.08 | N8: =IFERROR(M8/K8,0) -> 0.35016835 | O8: =IFERROR(L8/J8,0) -> 0.53910615 | P8: =IFERROR(L8/G8,0) -> 0.27571429
A9: R007 | B9: Uber | C9: Uber X | D9: 46085 | E9: 0.62361111 | F9: 0.63263889 | G9: =(F9-E9)*1440 -> 13 | H9: 1300-291 | I9: 1600-159 | J9: 8.61 | K9: 7.69 | L9: 5.08 | M9: =K9-L9 -> 2.61 | N9: =IFERROR(M9/K9,0) -> 0.33940182 | O9: =IFERROR(L9/J9,0) -> 0.59001161 | P9: =IFERROR(L9/G9,0) -> 0.39076923
A10: R012 | B10: Uber | C10: Uber X | D10: 46085 | E10: 0.78055556 | F10: 0.78958333 | G10: =(F10-E10)*1440 -> 13 | H10: 2760-127 | I10: 1500-288 | J10: 10.56 | K10: 8.96 | L10: 6.53 | M10: =K10-L10 -> 2.43 | N10: =IFERROR(M10/K10,0) -> 0.27120536 | O10: =IFERROR(L10/J10,0) -> 0.61837121 | P10: =IFERROR(L10/G10,0) -> 0.50230769
A11: R008 | B11: Uber | C11: Uber X | D11: 46085 | E11: 0.66805556 | F11: 0.68541667 | G11: =(F11-E11)*1440 -> 25 | H11: 1600-776 | I11: 2635-535 | J11: 19.36 | K11: 16.54 | L11: 13.22 | M11: =K11-L11 -> 3.32 | N11: =IFERROR(M11/K11,0) -> 0.20072551 | O11: =IFERROR(L11/J11,0) -> 0.68285124 | P11: =IFERROR(L11/G11,0) -> 0.5288 | Q11: 1.6
A12: R004 | B12: Bolt | C12: Economy | D12: 46085 | E12: 0.86875 | F12: 0.87847222 | G12: =(F12-E12)*1440 -> 14 | H12: 1700-008 | I12: 1150-200 | J12: 5.6 | K12: 7.18 | L12: 5.38 | M12: =K12-L12 -> 1.8 | N12: =IFERROR(M12/K12,0) -> 0.25069638 | O12: =IFERROR(L12/J12,0) -> 0.96071429 | P12: =IFERROR(L12/G12,0) -> 0.38428571
A13: R001 | B13: Bolt | C13: Bolt | D13: 46085 | E13: 0.77291667 | F13: 0.77708333 | G13: =(F13-E13)*1440 -> 6 | H13: 2790-022 | I13: 2790-379 | J13: 2.2 | K13: 6.12 | L13: 4.59 | M13: =K13-L13 -> 1.53 | N13: =IFERROR(M13/K13,0) -> 0.25 | O13: =IFERROR(L13/J13,0) -> 2.0863636 | P13: =IFERROR(L13/G13,0) -> 0.765
A14: R011 | B14: Uber | C14: Uber X Priority | D14: 46085 | E14: 0.75833333 | F14: 0.76111111 | G14: =(F14-E14)*1440 -> 4 | H14: 2790-114 | I14: 2790-196 | J14: 2.11 | K14: 6.98 | L14: 4.54 | M14: =K14-L14 -> 2.44 | N14: =IFERROR(M14/K14,0) -> 0.3495702 | O14: =IFERROR(L14/J14,0) -> 2.1516588 | P14: =IFERROR(L14/G14,0) -> 1.135
A15: R029 | B15: Uber | C15: Uber X | D15: 46086 | E15: 0.8875 | F15: 0.89791667 | G15: =(F15-E15)*1440 -> 15 | H15: 1200-479 | I15: 1700-087 | J15: 9.27 | K15: 5.96 | L15: 4.36 | M15: =K15-L15 -> 1.6 | N15: =IFERROR(M15/K15,0) -> 0.26845638 | O15: =IFERROR(L15/J15,0) -> 0.47033441 | P15: =IFERROR(L15/G15,0) -> 0.29066667
A16: R018 | B16: Bolt | C16: Economy | D16: 46086 | E16: 0.73333333 | F16: 0.74652778 | G16: =(F16-E16)*1440 -> 19 | H16: 2620-529 | I16: 1495-061 | J16: 16.3 | K16: 10.36 | L16: 7.77 | M16: =K16-L16 -> 2.59 | N16: =IFERROR(M16/K16,0) -> 0.25 | O16: =IFERROR(L16/J16,0) -> 0.47668712 | P16: =IFERROR(L16/G16,0) -> 0.40894737
A17: R017 | B17: Bolt | C17: Economy | D17: 46086 | E17: 0.68819444 | F17: 0.71597222 | G17: =(F17-E17)*1440 -> 40 | H17: 1300-474 | I17: 2620-535 | J17: 18.1 | K17: 10.07 | L17: 9.44 | M17: =K17-L17 -> 0.63 | N17: =IFERROR(M17/K17,0) -> 0.062562066 | O17: =IFERROR(L17/J17,0) -> 0.52154696 | P17: =IFERROR(L17/G17,0) -> 0.236
A18: R026 | B18: Uber | C18: Uber X | D18: 46086 | E18: 0.59513889 | F18: 0.60833333 | G18: =(F18-E18)*1440 -> 19 | H18: 2685-246 | I18: 1000-042 | J18: 8.58 | K18: 6.96 | L18: 4.76 | M18: =K18-L18 -> 2.2 | N18: =IFERROR(M18/K18,0) -> 0.31609195 | O18: =IFERROR(L18/J18,0) -> 0.55477855 | P18: =IFERROR(L18/G18,0) -> 0.25052632
A19: R024 | B19: Bolt | C19: Economy | D19: 46086 | E19: 0.86875 | F19: 0.87847222 | G19: =(F19-E19)*1440 -> 14 | H19: 1400-033 | I19: 1200-109 | J19: 6.5 | K19: 4.5 | L19: 4.13 | M19: =K19-L19 -> 0.37 | N19: =IFERROR(M19/K19,0) -> 0.082222222 | O19: =IFERROR(L19/J19,0) -> 0.63538462 | P19: =IFERROR(L19/G19,0) -> 0.295
A20: R028 | B20: Uber | C20: Uber X Priority | D20: 46086 | E20: 0.84027778 | F20: 0.85486111 | G20: =(F20-E20)*1440 -> 21 | H20: 1600-548 | I20: 1300-107 | J20: 9.93 | K20: 8.99 | L20: 6.9 | M20: =K20-L20 -> 2.09 | N20: =IFERROR(M20/K20,0) -> 0.23248053 | O20: =IFERROR(L20/J20,0) -> 0.69486405 | P20: =IFERROR(L20/G20,0) -> 0.32857143
A21: R025 | B21: Bolt | C21: Economy | D21: 46086 | E21: 0.90555556 | F21: 0.9125 | G21: =(F21-E21)*1440 -> 10 | H21: 1700-096 | I21: 1800-081 | J21: 3.9 | K21: 3.63 | L21: 3.02 | M21: =K21-L21 -> 0.61 | N21: =IFERROR(M21/K21,0) -> 0.16804408 | O21: =IFERROR(L21/J21,0) -> 0.77435897 | P21: =IFERROR(L21/G21,0) -> 0.302
A22: R023 | B22: Bolt | C22: Economy | D22: 46086 | E22: 0.80416667 | F22: 0.81666667 | G22: =(F22-E22)*1440 -> 18 | H22: 1500-179 | I22: 1350-025 | J22: 7.7 | K22: 7.3 | L22: 6.02 | M22: =K22-L22 -> 1.28 | N22: =IFERROR(M22/K22,0) -> 0.17534247 | O22: =IFERROR(L22/J22,0) -> 0.78181818 | P22: =IFERROR(L22/G22,0) -> 0.33444444
A23: R015 | B23: Bolt | C23: Economy | D23: 46086 | E23: 0.62986111 | F23: 0.64791667 | G23: =(F23-E23)*1440 -> 26 | H23: 1100-240 | I23: 1700-008 | J23: 7.7 | K23: 7.66 | L23: 6.31 | M23: =K23-L23 -> 1.35 | N23: =IFERROR(M23/K23,0) -> 0.17624021 | O23: =IFERROR(L23/J23,0) -> 0.81948052 | P23: =IFERROR(L23/G23,0) -> 0.24269231
... A30: R022 | B30: Bolt | C30: Economy | D30: 46086 | E30: 0.79652778 | F30: 0.80138889 | G30: =(F30-E30)*1440 -> 7 | H30: 1500-392 | I30: 1500-353 | J30: 1.3 | K30: 3.77 | L30: 4.04 | M30: =K30-L30 -> -0.27 | N30: =IFERROR(M30/K30,0) -> -0.071618037 | O30: =IFERROR(L30/J30,0) -> 3.1076923 | P30: =IFERROR(L30/G30,0) -> 0.57714286
A31: R038 | B31: Bolt | C31: Economy | D31: 46087 | E31: 0.69722222 | F31: 0.71805556 | G31: =(F31-E31)*1440 -> 30 | H31: 2744-017 | I31: 1750-065 | J31: 22.7 | K31: 10.3 | L31: 9.76 | M31: =K31-L31 -> 0.54 | N31: =IFERROR(M31/K31,0) -> 0.052427184 | O31: =IFERROR(L31/J31,0) -> 0.42995595 | P31: =IFERROR(L31/G31,0) -> 0.32533333 | Q31: 0.4
A32: R031 | B32: Uber | C32: Uber X | D32: 46087 | E32: 0.63611111 | F32: 0.64861111 | G32: =(F32-E32)*1440 -> 18 | H32: 1400-038 | I32: 1500-313 | J32: 11.92 | K32: 7.94 | L32: 5.16 | M32: =K32-L32 -> 2.78 | N32: =IFERROR(M32/K32,0) -> 0.35012594 | O32: =IFERROR(L32/J32,0) -> 0.43288591 | P32: =IFERROR(L32/G32,0) -> 0.28666667
A33: R046 | B33: Bolt | C33: Economy | D33: 46087 | E33: 0.91944444 | F33: 0.92986111 | G33: =(F33-E33)*1440 -> 15 | H33: 1990-083 | I33: 2615-043 | J33: 17.1 | K33: 8.55 | L33: 8.02 | M33: =K33-L33 -> 0.53 | N33: =IFERROR(M33/K33,0) -> 0.061988304 | O33: =IFERROR(L33/J33,0) -> 0.46900585 | P33: =IFERROR(L33/G33,0) -> 0.53466667
A34: R037 | B34: Bolt | C34: Economy | D34: 46087 | E34: 0.67708333 | F34: 0.69375 | G34: =(F34-E34)*1440 -> 24 | H34: 2790-218 | I34: 2785-171 | J34: 11.8 | K34: 7.3 | L34: 6.18 | M34: =K34-L34 -> 1.12 | N34: =IFERROR(M34/K34,0) -> 0.15342466 | O34: =IFERROR(L34/J34,0) -> 0.52372881 | P34: =IFERROR(L34/G34,0) -> 0.2575
A35: R042 | B35: Bolt | C35: Economy | D35: 46087 | E35: 0.80208333 | F35: 0.82291667 | G35: =(F35-E35)*1440 -> 30 | H35: 2735-472 | I35: 1070-051 | J35: 17.5 | K35: 9.94 | L35: 9.31 | M35: =K35-L35 -> 0.63 | N35: =IFERROR(M35/K35,0) -> 0.063380282 | O35: =IFERROR(L35/J35,0) -> 0.532 | P35: =IFERROR(L35/G35,0) -> 0.31033333
A36: R033 | B36: Uber | C36: Uber X | D36: 46087 | E36: 0.83888889 | F36: 0.85694444 | G36: =(F36-E36)*1440 -> 26 | H36: 1300-510 | I36: 1885-010 | J36: 14.98 | K36: 10.96 | L36: 8.11 | M36: =K36-L36 -> 2.85 | N36: =IFERROR(M36/K36,0) -> 0.2600365 | O36: =IFERROR(L36/J36,0) -> 0.54138852 | P36: =IFERROR(L36/G36,0) -> 0.31192308
A37: R043 | B37: Bolt | C37: Economy | D37: 46087 | E37: 0.86458333 | F37: 0.87847222 | G37: =(F37-E37)*1440 -> 20 | H37: 1990-307 | I37: 1070-234 | J37: 11.6 | K37: 6.74 | L37: 6.95 | M37: =K37-L37 -> -0.21 | N37: =IFERROR(M37/K37,0) -> -0.03115727 | O37: =IFERROR(L37/J37,0) -> 0.59913793 | P37: =IFERROR(L37/G37,0) -> 0.3475
A38: R036 | B38: Bolt | C38: Economy | D38: 46087 | E38: 0.65486111 | F38: 0.6625 | G38: =(F38-E38)*1440 -> 11 | H38: 1500-392 | I38: 2790-045 | J38: 6.2 | K38: 5.07 | L38: 3.8 | M38: =K38-L38 -> 1.27 | N38: =IFERROR(M38/K38,0) -> 0.2504931 | O38: =IFERROR(L38/J38,0) -> 0.61290323 | P38: =IFERROR(L38/G38,0) -> 0.34545455
A39: R041 | B39: Bolt | C39: Economy | D39: 46087 | E39: 0.78125 | F39: 0.79652778 | G39: =(F39-E39)*1440 -> 22 | H39: 2795-102 | I39: 2635-353 | J39: 16.2 | K39: 10.81 | L39: 10.22 | M39: =K39-L39 -> 0.59 | N39: =IFERROR(M39/K39,0) -> 0.054579093 | O39: =IFERROR(L39/J39,0) -> 0.6308642 | P39: =IFERROR(L39/G39,0) -> 0.46454545 | Q39: 0.35 | R39: 2.28
A40: R040 | B40: Bolt | C40: Economy | D40: 46087 | E40: 0.76180556 | F40: 0.77777778 | G40: =(F40-E40)*1440 -> 23 | H40: 1200-869 | I40: 2795-208 | J40: 10.3 | K40: 6.6 | L40: 7.07 | M40: =K40-L40 -> -0.47 | N40: =IFERROR(M40/K40,0) -> -0.071212121 | O40: =IFERROR(L40/J40,0) -> 0.68640777 | P40: =IFERROR(L40/G40,0) -> 0.3073913
A41: R034 | B41: Bolt | C41: Economy | D41: 46087 | E41: 0.55902778 | F41: 0.56875 | G41: =(F41-E41)*1440 -> 14 | H41: 2615-037 | I41: 2625-082 | J41: 6.2 | K41: 5.12 | L41: 4.27 | M41: =K41-L41 -> 0.85 | N41: =IFERROR(M41/K41,0) -> 0.16601563 | O41: =IFERROR(L41/J41,0) -> 0.68870968 | P41: =IFERROR(L41/G41,0) -> 0.305
A42: R035 | B42: Bolt | C42: Economy | D42: 46087 | E42: 0.62222222 | F42: 0.6375 | G42: =(F42-E42)*1440 -> 22 | H42: 1100-148 | I42: 1400-034 | J42: 7.3 | K42: 6.9 | L42: 5.17 | M42: =K42-L42 -> 1.73 | N42: =IFERROR(M42/K42,0) -> 0.25072464 | O42: =IFERROR(L42/J42,0) -> 0.70821918 | P42: =IFERROR(L42/G42,0) -> 0.235
A43: R044 | B43: Bolt | C43: Economy | D43: 46087 | E43: 0.87986111 | F43: 0.88680556 | G43: =(F43-E43)*1440 -> 10 | H43: 1070-066 | I43: 1700-008 | J43: 6.7 | K43: 6.8 | L43: 5.1 | M43: =K43-L43 -> 1.7 | N43: =IFERROR(M43/K43,0) -> 0.25 | O43: =IFERROR(L43/J43,0) -> 0.76119403 | P43: =IFERROR(L43/G43,0) -> 0.51 | R43: 1.14
A44: R030 | B44: Uber | C44: Share | D44: 46087 | E44: 0.56805556 | F44: 0.60486111 | G44: =(F44-E44)*1440 -> 53 | H44: 2625-005 | I44: 1100-316 | J44: 18.92 | K44: 17.35 | L44: 15.08 | M44: =K44-L44 -> 2.27 | N44: =IFERROR(M44/K44,0) -> 0.13083573 | O44: =IFERROR(L44/J44,0) -> 0.79704017 | P44: =IFERROR(L44/G44,0) -> 0.2845283
A45: R032 | B45: Uber | C45: Uber X Priority | D45: 46087 | E45: 0.82361111 | F45: 0.83263889 | G45: =(F45-E45)*1440 -> 13 | H45: 1050-020 | I45: 1300-319 | J45: 7.53 | K45: 9.97 | L45: 6.48 | M45: =K45-L45 -> 3.49 | N45: =IFERROR(M45/K45,0) -> 0.35005015 | O45: =IFERROR(L45/J45,0) -> 0.86055777 | P45: =IFERROR(L45/G45,0) -> 0.49846154
A46: R045 | B46: Bolt | C46: Bolt | D46: 46087 | E46: 0.8875 | F46: 0.89722222 | G46: =(F46-E46)*1440 -> 14 | H46: 1700-008 | I46: 1150-195 | J46: 5.4 | K46: 5.71 | L46: 4.75 | M46: =K46-L46 -> 0.96 | N46: =IFERROR(M46/K46,0) -> 0.16812609 | O46: =IFERROR(L46/J46,0) -> 0.87962963 | P46: =IFERROR(L46/G46,0) -> 0.33928571
A47: R039 | B47: Bolt | C47: Bolt | D47: 46087 | E47: 0.74236111 | F47: 0.75902778 | G47: =(F47-E47)*1440 -> 24 | H47: 1600-237 | I47: 1200-786 | J47: 9.5 | K47: 11.18 | L47: 8.38 | M47: =K47-L47 -> 2.8 | N47: =IFERROR(M47/K47,0) -> 0.25044723 | O47: =IFERROR(L47/J47,0) -> 0.88210526 | P47: =IFERROR(L47/G47,0) -> 0.34916667 | R47: 1.59
A48: R051 | B48: Bolt | C48: Economy | D48: 46088 | E48: 0.61805556 | F48: 0.64027778 | G48: =(F48-E48)*1440 -> 32 | H48: 1750-433 | I48: 2770-136 | J48: 22.1 | K48: 12.28 | L48: 9.31 | M48: =K48-L48 -> 2.97 | N48: =IFERROR(M48/K48,0) -> 0.24185668 | O48: =IFERROR(L48/J48,0) -> 0.42126697 | P48: =IFERROR(L48/G48,0) -> 0.2909375 | Q48: 0.4
A49: R052 | B49: Bolt | C49: Economy | D49: 46088 | E49: 0.64097222 | F49: 0.65972222 | G49: =(F49-E49)*1440 -> 27 | H49: 2770-103 | I49: 1600-404 | J49: 18.8 | K49: 9.39 | L49: 8.6 | M49: =K49-L49 -> 0.79 | N49: =IFERROR(M49/K49,0) -> 0.084132055 | O49: =IFERROR(L49/J49,0) -> 0.45744681 | P49: =IFERROR(L49/G49,0) -> 0.31851852
A50: R064 | B50: Uber | C50: Uber X | D50: 46088 | E50: 0.79097222 | F50: 0.81458333 | G50: =(F50-E50)*1440 -> 34 | H50: 1600-820 | I50: 1000-117 | J50: 23.6 | K50: 16.95 | L50: 11.2 | M50: =K50-L50 -> 5.75 | N50: =IFERROR(M50/K50,0) -> 0.33923304 | O50: =IFERROR(L50/J50,0) -> 0.47457627 | P50: =IFERROR(L50/G50,0) -> 0.32941176
A51: R063 | B51: Uber | C51: Uber X | D51: 46088 | E51: 0.76319444 | F51: 0.775 | G51: =(F51-E51)*1440 -> 17 | H51: 1750-410 | I51: 2790-017 | J51: 14.26 | K51: 9.93 | L51: 6.8 | M51: =K51-L51 -> 3.13 | N51: =IFERROR(M51/K51,0) -> 0.31520645 | O51: =IFERROR(L51/J51,0) -> 0.47685835 | P51: =IFERROR(L51/G51,0) -> 0.4
A52: R060 | B52: Uber | C52: Uber X | D52: 46088 | E52: 0.68680556 | F52: 0.7 | G52: =(F52-E52)*1440 -> 19 | H52: 1600-806 | I52: 1400-434 | J52: 14.46 | K52: 10.94 | L52: 7.11 | M52: =K52-L52 -> 3.83 | N52: =IFERROR(M52/K52,0) -> 0.35009141 | O52: =IFERROR(L52/J52,0) -> 0.49170124 | P52: =IFERROR(L52/G52,0) -> 0.37421053
A53: R059 | B53: Bolt | C53: Bolt | D53: 46088 | E53: 0.94861111 | F53: 0.96527778 | G53: =(F53-E53)*1440 -> 24 | H53: 1990-233 | I53: 2625-683 | J53: 21.1 | K53: 9.9 | L53: 10.6 | M53: =K53-L53 -> -0.7 | N53: =IFERROR(M53/K53,0) -> -0.070707071 | O53: =IFERROR(L53/J53,0) -> 0.50236967 | P53: =IFERROR(L53/G53,0) -> 0.44166667
A54: R056 | B54: Bolt | C54: Economy | D54: 46088 | E54: 0.84375 | F54: 0.85555556 | G54: =(F54-E54)*1440 -> 17 | H54: 1300-368 | I54: 1750-218 | J54: 12.2 | K54: 6.9 | L54: 6.33 | M54: =K54-L54 -> 0.57 | N54: =IFERROR(M54/K54,0) -> 0.082608696 | O54: =IFERROR(L54/J54,0) -> 0.51885246 | P54: =IFERROR(L54/G54,0) -> 0.37235294
A55: R048 | B55: Bolt | C55: Bolt | D55: 46088 | E55: 0.56319444 | F55: 0.57222222 | G55: =(F55-E55)*1440 -> 13 | H55: 2695-599 | I55: 1600-428 | J55: 10.6 | K55: 7.5 | L55: 5.62 | M55: =K55-L55 -> 1.88 | N55: =IFERROR(M55/K55,0) -> 0.25066667 | O55: =IFERROR(L55/J55,0) -> 0.53018868 | P55: =IFERROR(L55/G55,0) -> 0.43230769
A56: R047 | B56: Bolt | C56: Bolt | D56: 46088 | E56: 0.54583333 | F56: 0.55416667 | G56: =(F56-E56)*1440 -> 12 | H56: 2615-157 | I56: 2690-158 | J56: 9.6 | K56: 5.92 | L56: 5.55 | M56: =K56-L56 -> 0.37 | N56: =IFERROR(M56/K56,0) -> 0.0625 | O56: =IFERROR(L56/J56,0) -> 0.578125 | P56: =IFERROR(L56/G56,0) -> 0.4625 | R56: 1.27
A57: R054 | B57: Bolt | C57: Economy | D57: 46088 | E57: 0.78194444 | F57: 0.79097222 | G57: =(F57-E57)*1440 -> 13 | H57: 2790-135 | I57: 1600-145 | J57: 9.6 | K57: 7.71 | L57: 5.78 | M57: =K57-L57 -> 1.93 | N57: =IFERROR(M57/K57,0) -> 0.25032425 | O57: =IFERROR(L57/J57,0) -> 0.60208333 | P57: =IFERROR(L57/G57,0) -> 0.44461538 | R57: 1.32
A58: R058 | B58: Bolt | C58: Economy | D58: 46088 | E58: 0.92430556 | F58: 0.93125 | G58: =(F58-E58)*1440 -> 10 | H58: 1700-048 | I58: 1800-142 | J58: 6 | K58: 5.03 | L58: 3.77 | M58: =K58-L58 -> 1.26 | N58: =IFERROR(M58/K58,0) -> 0.25049702 | O58: =IFERROR(L58/J58,0) -> 0.62833333 | P58: =IFERROR(L58/G58,0) -> 0.377
A59: R062 | B59: Uber | C59: Uber X | D59: 46088 | E59: 0.73680556 | F59: 0.75 | G59: =(F59-E59)*1440 -> 19 | H59: 1400-203 | I59: 1750-010 | J59: 11.45 | K59: 8.96 | L59: 7.22 | M59: =K59-L59 -> 1.74 | N59: =IFERROR(M59/K59,0) -> 0.19419643 | O59: =IFERROR(L59/J59,0) -> 0.63056769 | P59: =IFERROR(L59/G59,0) -> 0.38
A60: R050 | B60: Bolt | C60: Economy | D60: 46088 | E60: 0.59861111 | F60: 0.61111111 | G60: =(F60-E60)*1440 -> 18 | H60: 1170-299 | I60: 1600-622 | J60: 8.2 | K60: 7.48 | L60: 5.61 | M60: =K60-L60 -> 1.87 | N60: =IFERROR(M60/K60,0) -> 0.25 | O60: =IFERROR(L60/J60,0) -> 0.68414634 | P60: =IFERROR(L60/G60,0) -> 0.31166667
A61: R065 | B61: Uber | C61: Uber X Priority | D61: 46088 | E61: 0.85902778 | F61: 0.875 | G61: =(F61-E61)*1440 -> 23 | H61: 1750-209 | I61: 1200-761 | J61: 12.39 | K61: 12.98 | L61: 8.52 | M61: =K61-L61 -> 4.46 | N61: =IFERROR(M61/K61,0) -> 0.34360555 | O61: =IFERROR(L61/J61,0) -> 0.68765133 | P61: =IFERROR(L61/G61,0) -> 0.37043478
A62: R055 | B62: Bolt | C62: Economy | D62: 46088 | E62: 0.82569444 | F62: 0.84305556 | G62: =(F62-E62)*1440 -> 25 | H62: 1150-023 | I62: 1300-361 | J62: 8.8 | K62: 6.52 | L62: 6.11 | M62: =K62-L62 -> 0.41 | N62: =IFERROR(M62/K62,0) -> 0.062883436 | O62: =IFERROR(L62/J62,0) -> 0.69431818 | P62: =IFERROR(L62/G62,0) -> 0.2444
A63: R049 | B63: Bolt | C63: Economy | D63: 46088 | E63: 0.57361111 | F63: 0.59236111 | G63: =(F63-E63)*1440 -> 27 | H63: 1750-002 | I63: 1100-471 | J63: 7.9 | K63: 6.3 | L63: 5.91 | M63: =K63-L63 -> 0.39 | N63: =IFERROR(M63/K63,0) -> 0.061904762 | O63: =IFERROR(L63/J63,0) -> 0.74810127 | P63: =IFERROR(L63/G63,0) -> 0.21888889 | R63: 1.36
A64: R061 | B64: Uber | C64: Uber X Priority | D64: 46088 | E64: 0.70416667 | F64: 0.71458333 | G64: =(F64-E64)*1440 -> 15 | H64: 1400-038 | I64: 1200-211 | J64: 6.42 | K64: 7.97 | L64: 5.18 | M64: =K64-L64 -> 2.79 | N64: =IFERROR(M64/K64,0) -> 0.35006274 | O64: =IFERROR(L64/J64,0) -> 0.80685358 | P64: =IFERROR(L64/G64,0) -> 0.34533333
A65: R053 | B65: Bolt | C65: Economy | D65: 46088 | E65: 0.72222222 | F65: 0.73472222 | G65: =(F65-E65)*1440 -> 18 | H65: 1200-479 | I65: 1300-012 | J65: 5.6 | K65: 5.9 | L65: 4.87 | M65: =K65-L65 -> 1.03 | N65: =IFERROR(M65/K65,0) -> 0.17457627 | O65: =IFERROR(L65/J65,0) -> 0.86964286 | P65: =IFERROR(L65/G65,0) -> 0.27055556
A66: R057 | B66: Bolt | C66: Bolt | D66: 46088 | E66: 0.89583333 | F66: 0.90625 | G66: =(F66-E66)*1440 -> 15 | H66: 1249-082 | I66: 1000-009 | J66: 5.7 | K66: 4.9 | L66: 5.06 | M66: =K66-L66 -> -0.16 | N66: =IFERROR(M66/K66,0) -> -0.032653061 | O66: =IFERROR(L66/J66,0) -> 0.8877193 | P66: =IFERROR(L66/G66,0) -> 0.33733333
A67: R067 | B67: Bolt | C67: Economy | D67: 46089 | E67: 0.59166667 | F67: 0.60138889 | G67: =(F67-E67)*1440 -> 14 | H67: 2695-687 | I67: 1500-392 | J67: 14.2 | K67: 7.84 | L67: 5.88 | M67: =K67-L67 -> 1.96 | N67: =IFERROR(M67/K67,0) -> 0.25 | O67: =IFERROR(L67/J67,0) -> 0.41408451 | P67: =IFERROR(L67/G67,0) -> 0.42
A68: R073 | B68: Bolt | C68: Economy | D68: 46089 | E68: 0.65694444 | F68: 0.66666667 | G68: =(F68-E68)*1440 -> 14 | H68: 2720-468 | I68: 1300-005 | J68: 9.2 | K68: 3.9 | L68: 4.18 | M68: =K68-L68 -> -0.28 | N68: =IFERROR(M68/K68,0) -> -0.071794872 | O68: =IFERROR(L68/J68,0) -> 0.45434783 | P68: =IFERROR(L68/G68,0) -> 0.29857143
A69: R068 | B69: Bolt | C69: Economy | D69: 46089 | E69: 0.60625 | F69: 0.61458333 | G69: =(F69-E69)*1440 -> 12 | H69: 1500-392 | I69: 1495-084 | J69: 9.4 | K69: 5.9 | L69: 4.42 | M69: =K69-L69 -> 1.48 | N69: =IFERROR(M69/K69,0) -> 0.25084746 | O69: =IFERROR(L69/J69,0) -> 0.47021277 | P69: =IFERROR(L69/G69,0) -> 0.36833333
A70: R070 | B70: Bolt | C70: Economy | D70: 46089 | E70: 0.62361111 | F70: 0.63055556 | G70: =(F70-E70)*1440 -> 10 | H70: 2795-102 | I70: 2790-045 | J70: 6.8 | K70: 3.9 | L70: 3.25 | M70: =K70-L70 -> 0.65 | N70: =IFERROR(M70/K70,0) -> 0.16666667 | O70: =IFERROR(L70/J70,0) -> 0.47794118 | P70: =IFERROR(L70/G70,0) -> 0.325
A71: R086 | B71: Uber | C71: Uber X Priority | D71: 46089 | E71: 0.82013889 | F71: 0.84583333 | G71: =(F71-E71)*1440 -> 37 | H71: 2694-026 | I71: 1449-003 | J71: 25.57 | K71: 15.91 | L71: 12.36 | M71: =K71-L71 -> 3.55 | N71: =IFERROR(M71/K71,0) -> 0.22313011 | O71: =IFERROR(L71/J71,0) -> 0.48337896 | P71: =IFERROR(L71/G71,0) -> 0.33405405
A72: R066 | B72: Bolt | C72: Economy | D72: 46089 | E72: 0.58125 | F72: 0.59027778 | G72: =(F72-E72)*1440 -> 13 | H72: 2625-435 | I72: 2695-689 | J72: 8.1 | K72: 5.3 | L72: 3.97 | M72: =K72-L72 -> 1.33 | N72: =IFERROR(M72/K72,0) -> 0.2509434 | O72: =IFERROR(L72/J72,0) -> 0.49012346 | P72: =IFERROR(L72/G72,0) -> 0.30538462
A73: R083 | B73: Bolt | C73: Economy | D73: 46089 | E73: 0.88194444 | F73: 0.89722222 | G73: =(F73-E73)*1440 -> 22 | H73: 1600-404 | I73: 2625-690 | J73: 22.5 | K73: 14.67 | L73: 12.1 | M73: =K73-L73 -> 2.57 | N73: =IFERROR(M73/K73,0) -> 0.17518746 | O73: =IFERROR(L73/J73,0) -> 0.53777778 | P73: =IFERROR(L73/G73,0) -> 0.55 | R73: 3.49
A74: R082 | B74: Bolt | C74: Economy | D74: 46089 | E74: 0.85694444 | F74: 0.86805556 | G74: =(F74-E74)*1440 -> 16 | H74: 1400-001 | I74: 1500-476 | J74: 9.6 | K74: 5.14 | L74: 5.3 | M74: =K74-L74 -> -0.16 | N74: =IFERROR(M74/K74,0) -> -0.031128405 | O74: =IFERROR(L74/J74,0) -> 0.55208333 | P74: =IFERROR(L74/G74,0) -> 0.33125
A75: R078 | B75: Bolt | C75: Economy | D75: 46089 | E75: 0.72986111 | F75: 0.74236111 | G75: =(F75-E75)*1440 -> 18 | H75: 1050-195 | I75: 1495-240 | J75: 11.6 | K75: 8.9 | L75: 6.67 | M75: =K75-L75 -> 2.23 | N75: =IFERROR(M75/K75,0) -> 0.2505618 | O75: =IFERROR(L75/J75,0) -> 0.575 | P75: =IFERROR(L75/G75,0) -> 0.37055556 | R75: 1.02
A76: R076 | B76: Bolt | C76: Economy | D76: 46089 | E76: 0.69861111 | F76: 0.71388889 | G76: =(F76-E76)*1440 -> 22 | H76: 1400-105 | I76: 1700-178 | J76: 12.1 | K76: 11.3 | L76: 8.47 | M76: =K76-L76 -> 2.83 | N76: =IFERROR(M76/K76,0) -> 0.25044248 | O76: =IFERROR(L76/J76,0) -> 0.7 | P76: =IFERROR(L76/G76,0) -> 0.385 | R76: 3.27
A77: R081 | B77: Bolt | C77: Economy | D77: 46089 | E77: 0.78819444 | F77: 0.79861111 | G77: =(F77-E77)*1440 -> 15 | H77: 1849-033 | I77: 2690-390 | J77: 10.2 | K77: 7.65 | L77: 7.17 | M77: =K77-L77 -> 0.48 | N77: =IFERROR(M77/K77,0) -> 0.062745098 | O77: =IFERROR(L77/J77,0) -> 0.70294118 | P77: =IFERROR(L77/G77,0) -> 0.478 | R77: 2.13
A78: R084 | B78: Uber | C78: Uber X | D78: 46089 | E78: 0.63402778 | F78: 0.63888889 | G78: =(F78-E78)*1440 -> 7 | H78: 2610-102 | I78: 1495-020 | J78: 4.57 | K78: 3.93 | L78: 3.31 | M78: =K78-L78 -> 0.62 | N78: =IFERROR(M78/K78,0) -> 0.15776081 | O78: =IFERROR(L78/J78,0) -> 0.72428884 | P78: =IFERROR(L78/G78,0) -> 0.47285714
A79: R085 | B79: Uber | C79: Uber X Priority | D79: 46089 | E79: 0.74166667 | F79: 0.75277778 | G79: =(F79-E79)*1440 -> 16 | H79: 1495-098 | I79: 1200-834 | J79: 7.97 | K79: 6.98 | L79: 5.85 | M79: =K79-L79 -> 1.13 | N79: =IFERROR(M79/K79,0) -> 0.16189112 | O79: =IFERROR(L79/J79,0) -> 0.73400251 | P79: =IFERROR(L79/G79,0) -> 0.365625
A80: R079 | B80: Bolt | C80: Economy | D80: 46089 | E80: 0.75972222 | F80: 0.77291667 | G80: =(F80-E80)*1440 -> 19 | H80: 1250-100 | I80: 1500-039 | J80: 10.5 | K80: 10.9 | L80: 8.17 | M80: =K80-L80 -> 2.73 | N80: =IFERROR(M80/K80,0) -> 0.25045872 | O80: =IFERROR(L80/J80,0) -> 0.77809524 | P80: =IFERROR(L80/G80,0) -> 0.43 | R80: 2.29
A81: R080 | B81: Bolt | C81: Economy | D81: 46089 | E81: 0.77430556 | F81: 0.78611111 | G81: =(F81-E81)*1440 -> 17 | H81: 1500-392 | I81: 1990-291 | J81: 6.19 | K81: 6.19 | L81: 5.8 | M81: =K81-L81 -> 0.39 | N81: =IFERROR(M81/K81,0) -> 0.063004847 | O81: =IFERROR(L81/J81,0) -> 0.93699515 | P81: =IFERROR(L81/G81,0) -> 0.34117647 | R81: 0.72
A82: R072 | B82: bolt | C82: Economy | D82: 46089 | E82: 0.64652778 | F82: 0.65347222 | G82: =(F82-E82)*1440 -> 10 | H82: 1400-157 | I82: 2720-062 | J82: 6.1 | K82: 7.9 | L82: 7.4 | M82: =K82-L82 -> 0.5 | N82: =IFERROR(M82/K82,0) -> 0.063291139 | O82: =IFERROR(L82/J82,0) -> 1.2131148 | P82: =IFERROR(L82/G82,0) -> 0.74 | R82: 5.06
A83: R074 | B83: Bolt | C83: Economy | D83: 46089 | E83: 0.67013889 | F83: 0.67569444 | G83: =(F83-E83)*1440 -> 8 | H83: 1300-344 | I83: 1300-416 | J83: 3 | K83: 5.39 | L83: 4.04 | M83: =K83-L83 -> 1.35 | N83: =IFERROR(M83/K83,0) -> 0.25046382 | O83: =IFERROR(L83/J83,0) -> 1.3466667 | P83: =IFERROR(L83/G83,0) -> 0.505
A84: R077 | B84: Bolt | C84: Economy | D84: 46089 | E84: 0.71736111 | F84: 0.72222222 | G84: =(F84-E84)*1440 -> 7 | H84: 1700-141 | I84: 1050-190 | J84: 2.8 | K84: 5 | L84: 4.13 | M84: =K84-L84 -> 0.87 | N84: =IFERROR(M84/K84,0) -> 0.174 | O84: =IFERROR(L84/J84,0) -> 1.475 | P84: =IFERROR(L84/G84,0) -> 0.59 | R84: 1.15
A85: R069 | B85: Bolt | C85: Economy | D85: 46089 | E85: 0.61666667 | F85: 0.62152778 | G85: =(F85-E85)*1440 -> 7 | H85: 1495-034 | I85: 1495-724 | J85: 1.9 | K85: 4 | L85: 3 | M85: =K85-L85 -> 1 | N85: =IFERROR(M85/K85,0) -> 0.25 | O85: =IFERROR(L85/J85,0) -> 1.5789474 | P85: =IFERROR(L85/G85,0) -> 0.42857143
A86: R071 | B86: Bolt | C86: Economy | D86: 46089 | E86: 0.63055556 | F86: 0.63472222 | G86: =(F86-E86)*1440 -> 6 | H86: 2790-143 | I86: 2610-110 | J86: 1.7 | K86: 3.85 | L86: 2.89 | M86: =K86-L86 -> 0.96 | N86: =IFERROR(M86/K86,0) -> 0.24935065 | O86: =IFERROR(L86/J86,0) -> 1.7 | P86: =IFERROR(L86/G86,0) -> 0.48166667
A87: R087 | B87: Uber | C87: Uber X Priority | D87: 46089 | E87: 0.87013889 | F87: 0.87430556 | G87: =(F87-E87)*1440 -> 6 | H87: 1500-423 | I87: 1700-046 | J87: 2.61 | K87: 8.97 | L87: 6.84 | M87: =K87-L87 -> 2.13 | N87: =IFERROR(M87/K87,0) -> 0.23745819 | O87: =IFERROR(L87/J87,0) -> 2.6206897 | P87: =IFERROR(L87/G87,0) -> 1.14
A88: R075 | B88: Bolt | C88: Economy | D88: 46089 | E88: 0.69166667 | F88: 0.69444444 | G88: =(F88-E88)*1440 -> 4 | H88: 1300-338 | I88: 1300-085 | J88: 0.8 | K88: 7.32 | L88: 5.49 | M88: =K88-L88 -> 1.83 | N88: =IFERROR(M88/K88,0) -> 0.25 | O88: =IFERROR(L88/J88,0) -> 6.8625 | P88: =IFERROR(L88/G88,0) -> 1.3725 | R88: 3.47
A89: R088 | B89: Uber | C89: Uber X | D89: 46090 | E89: 0.60694444 | F89: 0.62222222 | G89: =(F89-E89)*1440 -> 22 | H89: 1800-399 | I89: 1495-130 | J89: 22.17 | K89: 9.95 | L89: 6.47 | M89: =K89-L89 -> 3.48 | N89: =IFERROR(M89/K89,0) -> 0.34974874 | O89: =IFERROR(L89/J89,0) -> 0.29183581 | P89: =IFERROR(L89/G89,0) -> 0.29409091
A90: R103 | B90: Bolt | C90: Economy | D90: 46090 | E90: 0.85833333 | F90: 0.87638889 | G90: =(F90-E90)*1440 -> 26 | H90: 1495-682 | I90: 1700-305 | J90: 18.4 | K90: 10.21 | L90: 7.66 | M90: =K90-L90 -> 2.55 | N90: =IFERROR(M90/K90,0) -> 0.24975514 | O90: =IFERROR(L90/J90,0) -> 0.41630435 | P90: =IFERROR(L90/G90,0) -> 0.29461538
A91: R102 | B91: Bolt | C91: Economy | D91: 46090 | E91: 0.84305556 | F91: 0.85625 | G91: =(F91-E91)*1440 -> 19 | H91: 1750-137 | I91: 2795-235 | J91: 15 | K91: 6.9 | L91: 6.47 | M91: =K91-L91 -> 0.43 | N91: =IFERROR(M91/K91,0) -> 0.062318841 | O91: =IFERROR(L91/J91,0) -> 0.43133333 | P91: =IFERROR(L91/G91,0) -> 0.34052632
A92: R096 | B92: Bolt | C92: Economy | D92: 46090 | E92: 0.57013889 | F92: 0.59097222 | G92: =(F92-E92)*1440 -> 30 | H92: 2615-276 | I92: 1170-289 | J92: 22.6 | K92: 11.9 | L92: 9.91 | M92: =K92-L92 -> 1.99 | N92: =IFERROR(M92/K92,0) -> 0.16722689 | O92: =IFERROR(L92/J92,0) -> 0.43849558 | P92: =IFERROR(L92/G92,0) -> 0.33033333
A93: R089 | B93: Uber | C93: Uber X | D93: 46090 | E93: 0.64444444 | F93: 0.65138889 | G93: =(F93-E93)*1440 -> 10 | H93: 2675-220 | I93: 1500-431 | J93: 7.27 | K93: 4.95 | L93: 3.22 | M93: =K93-L93 -> 1.73 | N93: =IFERROR(M93/K93,0) -> 0.34949495 | O93: =IFERROR(L93/J93,0) -> 0.44291609 | P93: =IFERROR(L93/G93,0) -> 0.322
A94: R098 | B94: Bolt | C94: Economy | D94: 46090 | E94: 0.62916667 | F94: 0.64097222 | G94: =(F94-E94)*1440 -> 17 | H94: 1495-159 | I94: 2675-382 | J94: 14.5 | K94: 8.57 | L94: 6.43 | M94: =K94-L94 -> 2.14 | N94: =IFERROR(M94/K94,0) -> 0.24970828 | O94: =IFERROR(L94/J94,0) -> 0.44344828 | P94: =IFERROR(L94/G94,0) -> 0.37823529
A95: R095 | B95: Uber | C95: Uber X | D95: 46090 | E95: 0.90069444 | F95: 0.90625 | G95: =(F95-E95)*1440 -> 8 | H95: 1800-399 | I95: 2695-699 | J95: 6.87 | K95: 4.93 | L95: 3.53 | M95: =K95-L95 -> 1.4 | N95: =IFERROR(M95/K95,0) -> 0.28397566 | O95: =IFERROR(L95/J95,0) -> 0.51382824 | P95: =IFERROR(L95/G95,0) -> 0.44125
A96: R090 | B96: Uber | C96: Uber X | D96: 46090 | E96: 0.70625 | F96: 0.72083333 | G96: =(F96-E96)*1440 -> 21 | H96: 1495-133 | I96: 1600-404 | J96: 13.12 | K96: 10.23 | L96: 7.26 | M96: =K96-L96 -> 2.97 | N96: =IFERROR(M96/K96,0) -> 0.29032258 | O96: =IFERROR(L96/J96,0) -> 0.55335366 | P96: =IFERROR(L96/G96,0) -> 0.34571429
A97: R093 | B97: Uber | C97: Uber X | D97: 46090 | E97: 0.79236111 | F97: 0.80625 | G97: =(F97-E97)*1440 -> 20 | H97: 1495-037 | I97: 1675-275 | J97: 12.97 | K97: 8.96 | L97: 7.18 | M97: =K97-L97 -> 1.78 | N97: =IFERROR(M97/K97,0) -> 0.19866071 | O97: =IFERROR(L97/J97,0) -> 0.5535852 | P97: =IFERROR(L97/G97,0) -> 0.359
A98: R099 | B98: Bolt | C98: Economy | D98: 46090 | E98: 0.66319444 | F98: 0.675 | G98: =(F98-E98)*1440 -> 17 | H98: 1600-165 | I98: 1990-094 | J98: 8.2 | K98: 6.33 | L98: 4.75 | M98: =K98-L98 -> 1.58 | N98: =IFERROR(M98/K98,0) -> 0.24960506 | O98: =IFERROR(L98/J98,0) -> 0.57926829 | P98: =IFERROR(L98/G98,0) -> 0.27941176
A99: R100 | B99: Bolt | C99: Economy | D99: 46090 | E99: 0.67638889 | F99: 0.69236111 | G99: =(F99-E99)*1440 -> 23 | H99: 1990-094 | I99: 1070-146 | J99: 10.2 | K99: 9.43 | L99: 7.07 | M99: =K99-L99 -> 2.36 | N99: =IFERROR(M99/K99,0) -> 0.25026511 | O99: =IFERROR(L99/J99,0) -> 0.69313725 | P99: =IFERROR(L99/G99,0) -> 0.3073913 | R99: 0.87
A100: R091 | B100: Uber | C100: Uber X | D100: 46090 | E100: 0.73125 | F100: 0.75694444 | G100: =(F100-E100)*1440 -> 37 | H100: 1700-090 | I100: 2730-205 | J100: 16.07 | K100: 14.94 | L100: 11.51 | M100: =K100-L100 -> 3.43 | N100: =IFERROR(M100/K100,0) -> 0.22958501 | O100: =IFERROR(L100/J100,0) -> 0.71624144 | P100: =IFERROR(L100/G100,0) -> 0.31108108
A101: R097 | B101: Bolt | C101: Economy | D101: 46090 | E101: 0.59652778 | F101: 0.60902778 | G101: =(F101-E101)*1440 -> 18 | H101: 1150-011 | I101: 1800-142 | J101: 7.5 | K101: 6.9 | L101: 5.69 | M101: =K101-L101 -> 1.21 | N101: =IFERROR(M101/K101,0) -> 0.17536232 | O101: =IFERROR(L101/J101,0) -> 0.75866667 | P101: =IFERROR(L101/G101,0) -> 0.31611111
A102: R094 | B102: Uber | C102: Uber X | D102: 46090 | E102: 0.8125 | F102: 0.81944444 | G102: =(F102-E102)*1440 -> 10 | H102: 2650-505 | I102: 2675-301 | J102: 5.63 | K102: 5.99 | L102: 4.48 | M102: =K102-L102 -> 1.51 | N102: =IFERROR(M102/K102,0) -> 0.25208681 | O102: =IFERROR(L102/J102,0) -> 0.79573712 | P102: =IFERROR(L102/G102,0) -> 0.448
A103: R101 | B103: Bolt | C103: Economy | D103: 46090 | E103: 0.69375 | F103: 0.70277778 | G103: =(F103-E103)*1440 -> 13 | H103: 1070-165 | I103: 2790-044 | J103: 6.7 | K103: 7.22 | L103: 5.54 | M103: =K103-L103 -> 1.68 | N103: =IFERROR(M103/K103,0) -> 0.23268698 | O103: =IFERROR(L103/J103,0) -> 0.82686567 | P103: =IFERROR(L103/G103,0) -> 0.42615385 | R103: 1.55
A104: R092 | B104: Uber | C104: Uber X | D104: 46090 | E104: 0.76180556 | F104: 0.76944444 | G104: =(F104-E104)*1440 -> 11 | H104: 2790-372 | I104: 1495-028 | J104: 6.27 | K104: 5.36 | L104: 5.21 | M104: =K104-L104 -> 0.15 | N104: =IFERROR(M104/K104,0) -> 0.027985075 | O104: =IFERROR(L104/J104,0) -> 0.83094099 | P104: =IFERROR(L104/G104,0) -> 0.47363636
A105: R114 | B105: Uber | C105: Uber X | D105: 46092 | E105: 0.56944444 | F105: 0.58611111 | G105: =(F105-E105)*1440 -> 24 | H105: 2615-080 | I105: 1900-221 | J105: 23.07 | K105: 12.96 | L105: 8.97 | M105: =K105-L105 -> 3.99 | N105: =IFERROR(M105/K105,0) -> 0.30787037 | O105: =IFERROR(L105/J105,0) -> 0.38881664 | P105: =IFERROR(L105/G105,0) -> 0.37375
A106: R113 | B106: Bolt | C106: Economy | D106: 46092 | E106: 0.89305556 | F106: 0.90625 | G106: =(F106-E106)*1440 -> 19 | H106: 1800-399 | I106: 2625-088 | J106: 13.1 | K106: 7.9 | L106: 5.92 | M106: =K106-L106 -> 1.98 | N106: =IFERROR(M106/K106,0) -> 0.25063291 | O106: =IFERROR(L106/J106,0) -> 0.4519084 | P106: =IFERROR(L106/G106,0) -> 0.31157895
...

Sheet Fuel
A1: Week | B1: Refuel_Date | C1: PRIO_Amount_EUR | D1: Liters | E1: EUR_per_Liter | F1: Week_Km | G1: Fuel_Cost_per_Km | H1: Week_Earnings_EUR | I1: Fuel_Pct_Earnings | J1: Net_Profit_EUR | K1: Notes
A2: W20/2026 | B2: 12/05/2026 | C2: 55 | D2: 42.3 | E2: =IFERROR(C2/D2,0) -> 1.3002364 | F2: =IFERROR(SUMPRODUCT((TEXT(DATEVALUE(Rides!D2:D4999),"YYYY-WW")=TEXT(DATEVALUE(B2),"YYYY-WW"))*Rides!J2:J4999),0) -> 0 | G2: =IFERROR(C2/F2,0) -> 0 | H2: =IFERROR(SUMPRODUCT((TEXT(DATEVALUE(Rides!D2:D4999),"YYYY-WW")=TEXT(DATEVALUE(B2),"YYYY-WW"))*Rides!L2:L4999),0) -> 0 | I2: =IFERROR(C2/H2,0) -> 0 | J2: =IFERROR(H2-C2,0) -> -55
A3: W19/2026 | B3: 05/05/2026 | C3: 48.5 | D3: 37.1 | E3: =IFERROR(C3/D3,0) -> 1.3072776 | F3: =IFERROR(SUMPRODUCT((TEXT(DATEVALUE(Rides!D2:D4999),"YYYY-WW")=TEXT(DATEVALUE(B3),"YYYY-WW"))*Rides!J2:J4999),0) -> 0 | G3: =IFERROR(C3/F3,0) -> 0 | H3: =IFERROR(SUMPRODUCT((TEXT(DATEVALUE(Rides!D2:D4999),"YYYY-WW")=TEXT(DATEVALUE(B3),"YYYY-WW"))*Rides!L2:L4999),0) -> 0 | I3: =IFERROR(C3/H3,0) -> 0 | J3: =IFERROR(H3-C3,0) -> -48.5
A4: TOTAL | C4: =SUM(C2:C3) -> 103.5 | D4: =SUM(D2:D3) -> 79.4 | E4: =IFERROR(C4/D4,0) -> 1.3035264 | F4: =SUM(F2:F3) -> 0 | G4: =IFERROR(C4/F4,0) -> 0 | H4: =SUM(H2:H3) -> 0 | I4: =IFERROR(C4/H4,0) -> 0 | J4: =SUM(J2:J3) -> -103.5

Sheet Monthly_Summary
B1: 📊 MONTHLY SUMMARY — TVDE
B3: RIDES
B4: Total Rides | C4: =COUNTA(Rides!A2:A4999) -> 2600
B5: Total Distance (Km) | C5: =SUM(Rides!J2:J4999) -> 23951.11
B6: Total Duration (Min) | C6: =SUM(Rides!G2:G4999) -> 40785
B7: Total Duration (Hours) | C7: =IFERROR(C6/60,0) -> 679.75
B8: Avg Distance per Ride (Km) | C8: =IFERROR(C5/C4,0) -> 9.2119654
B9: Avg Duration per Ride (Min) | C9: =IFERROR(C6/C4,0) -> 15.686538
B11: EARNINGS
B12: Total Client Fare (€) | C12: =SUM(Rides!K2:K4999) -> 20630.36
B13: Total Driver Earnings (€) | C13: =SUM(Rides!L2:L4999) -> 15986.7
B14: Total Platform Fees (€) | C14: =SUM(Rides!M2:M4999) -> 4643.66
B15: Avg Platform Fee % | C15: =IFERROR(C14/C12,0) -> 0.22508866
B16: Earnings per Km (€) | C16: =IFERROR(C13/C5,0) -> 0.6674722
B17: Earnings per Hour (€) | C17: =IFERROR(C13/C7,0) -> 23.518499
B18: Earnings per Ride (€) | C18: =IFERROR(C13/C4,0) -> 6.1487308
B20: BY PLATFORM
B21: Uber — Total Rides | C21: =COUNTIF(Rides!B2:B4999,"Uber") -> 1099
B22: Uber — Driver Earnings (€) | C22: =SUMIF(Rides!B2:B4999,"Uber",Rides!L2:L4999) -> 6903.59
B23: Bolt — Total Rides | C23: =COUNTIF(Rides!B2:B4999,"Bolt") -> 1272
B24: Bolt — Driver Earnings (€) | C24: =SUMIF(Rides!B2:B4999,"Bolt",Rides!L2:L4999) -> 7918.26
B26: FUEL
B27: Total Fuel Cost — PRIO (€) | C27: =SUM(Fuel!C2:C5000) -> 207
B28: Avg Fuel Cost per Km (€) | C28: =IFERROR(C27/C5,0) -> 0.0086426057
B29: Fuel % of Driver Earnings | C29: =IFERROR(C27/C13,0) -> 0.012948263
B30: Net Profit after Fuel (€) | C30: =IFERROR(C13-C27,0) -> 15779.7
B31: Net Profit per Hour (€) | C31: =IFERROR(C30/C7,0) -> 23.213976

Sheet Data_Dictionary
B1: DATA DICTIONARY — TVDE Rides Database
B3: Field | C3: Description | D3: Example | E3: Entry Type
B4: — RIDES TABLE —
B5: Ride_ID | C5: Unique sequential ride identifier | D5: R001 | E5: Manual
B6: Platform | C6: Ride-hailing app used | D6: Uber / Bolt | E6: Manual
B7: Category | C7: Service tier offered by the platform | D7: UberX / Economy | E7: Manual
B8: Date | C8: Date the ride took place (DD/MM/YYYY) | D8: 13/05/2026 | E8: Manual
B9: Day_of_Week | C9: Day of the week | D9: Wednesday | E9: Manual
B10: Start_Time | C10: Ride start time (HH:MM) | D10: 19:21 | E10: Manual
B11: End_Time | C11: Ride end time (HH:MM) | D11: 19:38 | E11: Manual
B12: Duration_Min | C12: Ride duration in minutes (decimal) | D12: 17.58 | E12: Manual
B13: Origin_PostCode | C13: Postal code where the ride started | D13: 2685-343 | E13: Manual
B14: Dest_PostCode | C14: Postal code where the ride ended | D14: 2625-583 | E14: Manual
B15: Distance_Km | C15: Total distance of the ride in kilometres | D15: 18.31 | E15: Manual
B16: Client_Fare_EUR | C16: Total amount paid by the passenger | D16: 11.96 € | E16: Manual
... B21: EUR_per_Min | C21: Driver earnings divided by duration | D21: 0.46 €/min | E21: Formula
B22: — FUEL TABLE —
B23: Week | C23: Week reference label | D23: W20/2026 | E23: Manual
B24: Refuel_Date | C24: Date of PRIO refuel | D24: 12/05/2026 | E24: Manual
B25: PRIO_Amount_EUR | C25: Total amount paid at PRIO that week | D25: 55.00 € | E25: Manual
B26: Liters | C26: Litres fuelled that week | D26: 42.30 L | E26: Manual
B27: EUR_per_Liter | C27: Price per litre (auto-calculated) | D27: 1.30 €/L | E27: Formula
B28: Week_Km | C28: Total km driven that week (from Rides tab) | D28: 210.5 km | E28: Formula (cross-sheet)
B29: Fuel_Cost_per_Km | C29: Fuel cost divided by km driven | D29: 0.26 €/km | E29: Formula
B30: Week_Earnings_EUR | C30: Total driver earnings that week (from Rides tab) | D30: 92.40 € | E30: Formula (cross-sheet)
B31: Fuel_Pct_Earnings | C31: Fuel cost as % of driver earnings | D31: 59.5% | E31: Formula
B32: Net_Profit_EUR | C32: Driver earnings minus fuel cost | D32: 37.40 € | E32: Formula
